{
  "info": {
    "_postman_id": "fe8f8fc0-48dc-4ed1-b3ae-3734652e8a49",
    "name": "HDO",
    "schema": "https://schema.getpostman.com/json/collection/v2.1.0/collection.json",
    "_exporter_id": "18339271",
    "_collection_link": "https://go.postman.co/collection/18339271-fe8f8fc0-48dc-4ed1-b3ae-3734652e8a49?source=collection_link"
  },
  "item": [
    {
      "name": "Auth",
      "item": [
        {
          "name": "Login",
          "event": [
            {
              "listen": "test",
              "script": {
                "exec": [
                  "pm.test(\"Login OK\", function () {",
                  "  pm.response.to.have.status(200);",
                  "});",
                  "",
                  "const json = pm.response.json();",
                  "pm.environment.set(\"token\", json.token);",
                  "pm.environment.set(\"refreshToken\", json.refreshToken);",
                  "pm.environment.set(\"userId\", json.user.id)"
                ],
                "type": "text/javascript",
                "packages": {},
                "requests": {}
              }
            }
          ],
          "request": {
            "method": "POST",
            "header": [],
            "body": {
              "mode": "raw",
              "raw": "{\n    \"email\": \"luc.cristovam10@gmail.com\",\n    \"password\": \"test123\"\n}",
              "options": {
                "raw": {
                  "language": "json"
                }
              }
            },
            "url": {
              "raw": "{{baseUrl}}/login",
              "host": [
                "{{baseUrl}}"
              ],
              "path": [
                "login"
              ]
            }
          },
          "response": []
        },
        {
          "name": "Refresh",
          "event": [
            {
              "listen": "test",
              "script": {
                "exec": [
                  "pm.test(\"Refresh OK\", function () {",
                  "  pm.response.to.have.status(200);",
                  "});",
                  "",
                  "const json = pm.response.json();",
                  "pm.environment.set(\"token\", json.token);",
                  "pm.environment.set(\"refreshToken\", json.refreshToken);"
                ],
                "type": "text/javascript",
                "packages": {}
              }
            }
          ],
          "request": {
            "method": "POST",
            "header": [],
            "body": {
              "mode": "raw",
              "raw": "{\n    \"refreshToken\": \"{{refreshToken}}\"\n}",
              "options": {
                "raw": {
                  "language": "json"
                }
              }
            },
            "url": {
              "raw": "{{baseUrl}}/refresh",
              "host": [
                "{{baseUrl}}"
              ],
              "path": [
                "refresh"
              ]
            }
          },
          "response": []
        },
        {
          "name": "Me",
          "event": [
            {
              "listen": "prerequest",
              "script": {
                "exec": [
                  "pm.test(\"User OK\", function () {",
                  "  pm.response.to.have.status(200);",
                  "});",
                  "",
                  "const json = pm.response.json();",
                  "pm.environment.set(\"userId\", json.id)"
                ],
                "type": "text/javascript",
                "packages": {}
              }
            }
          ],
          "request": {
            "auth": {
              "type": "bearer",
              "bearer": [
                {
                  "key": "token",
                  "value": "{{token}}",
                  "type": "string"
                }
              ]
            },
            "method": "GET",
            "header": [],
            "url": {
              "raw": "{{baseUrl}}/me",
              "host": [
                "{{baseUrl}}"
              ],
              "path": [
                "me"
              ]
            }
          },
          "response": []
        }
      ]
    },
    {
      "name": "Patients",
      "item": [
        {
          "name": "Create Patient",
          "event": [
            {
              "listen": "test",
              "script": {
                "exec": [
                  "pm.test(\"Create OK\", function () {",
                  "  pm.response.to.have.status(200);",
                  "});",
                  "",
                  "const json = pm.response.json();",
                  "pm.environment.set(\"patientId\", json.id);"
                ],
                "type": "text/javascript",
                "packages": {}
              }
            }
          ],
          "request": {
            "auth": {
              "type": "bearer",
              "bearer": [
                {
                  "key": "token",
                  "value": "{{token}}",
                  "type": "string"
                }
              ]
            },
            "method": "POST",
            "header": [],
            "body": {
              "mode": "raw",
              "raw": "{\n    \"name\": \"Lucas Sntoss\",\n    \"phone\": \"98184963021\",\n    \"document\": \"06844048501\"\n}",
              "options": {
                "raw": {
                  "language": "json"
                }
              }
            },
            "url": {
              "raw": "{{baseUrl}}/patients",
              "host": [
                "{{baseUrl}}"
              ],
              "path": [
                "patients"
              ]
            }
          },
          "response": []
        },
        {
          "name": "Update Patient",
          "request": {
            "auth": {
              "type": "bearer",
              "bearer": [
                {
                  "key": "token",
                  "value": "{{token}}",
                  "type": "string"
                }
              ]
            },
            "method": "PUT",
            "header": [],
            "body": {
              "mode": "raw",
              "raw": "{\n    \"name\": \"Lucas Satos\",\n    \"phone\": \"981849630\"\n}",
              "options": {
                "raw": {
                  "language": "json"
                }
              }
            },
            "url": {
              "raw": "{{baseUrl}}/patients/{{patientId}}",
              "host": [
                "{{baseUrl}}"
              ],
              "path": [
                "patients",
                "{{patientId}}"
              ]
            }
          },
          "response": []
        },
        {
          "name": "List Patients",
          "request": {
            "auth": {
              "type": "bearer",
              "bearer": [
                {
                  "key": "token",
                  "value": "{{token}}",
                  "type": "string"
                }
              ]
            },
            "method": "GET",
            "header": [],
            "url": {
              "raw": "{{baseUrl}}/patients",
              "host": [
                "{{baseUrl}}"
              ],
              "path": [
                "patients"
              ]
            }
          },
          "response": []
        },
        {
          "name": "Delete Patient",
          "request": {
            "auth": {
              "type": "bearer",
              "bearer": [
                {
                  "key": "token",
                  "value": "{{token}}",
                  "type": "string"
                }
              ]
            },
            "method": "DELETE",
            "header": [],
            "url": {
              "raw": "{{baseUrl}}/patients/{{patientId}}",
              "host": [
                "{{baseUrl}}"
              ],
              "path": [
                "patients",
                "{{patientId}}"
              ]
            }
          },
          "response": []
        }
      ]
    },
    {
      "name": "Procedures",
      "item": [
        {
          "name": "Create Procedure",
          "event": [
            {
              "listen": "test",
              "script": {
                "exec": [
                  "pm.test(\"Create OK\", function () {",
                  "  pm.response.to.have.status(200);",
                  "});",
                  "",
                  "const json = pm.response.json();",
                  "pm.environment.set(\"procedureId\", json.id);"
                ],
                "type": "text/javascript",
                "packages": {}
              }
            }
          ],
          "request": {
            "auth": {
              "type": "bearer",
              "bearer": [
                {
                  "key": "token",
                  "value": "{{token}}",
                  "type": "string"
                }
              ]
            },
            "method": "POST",
            "header": [],
            "body": {
              "mode": "raw",
              "raw": "{\n    \"description\": \"Teste\",\n    \"durationMin\": 30\n}",
              "options": {
                "raw": {
                  "language": "json"
                }
              }
            },
            "url": {
              "raw": "{{baseUrl}}/procedures",
              "host": [
                "{{baseUrl}}"
              ],
              "path": [
                "procedures"
              ]
            }
          },
          "response": []
        },
        {
          "name": "Update Procedure",
          "request": {
            "auth": {
              "type": "bearer",
              "bearer": [
                {
                  "key": "token",
                  "value": "{{token}}",
                  "type": "string"
                }
              ]
            },
            "method": "PUT",
            "header": [],
            "body": {
              "mode": "raw",
              "raw": "{\n    \"description\": \"Teste mudançai\"\n}",
              "options": {
                "raw": {
                  "language": "json"
                }
              }
            },
            "url": {
              "raw": "{{baseUrl}}/procedures/{{procedureId}}",
              "host": [
                "{{baseUrl}}"
              ],
              "path": [
                "procedures",
                "{{procedureId}}"
              ]
            }
          },
          "response": []
        },
        {
          "name": "List Procedure",
          "request": {
            "auth": {
              "type": "bearer",
              "bearer": [
                {
                  "key": "token",
                  "value": "{{token}}",
                  "type": "string"
                }
              ]
            },
            "method": "GET",
            "header": [],
            "url": {
              "raw": "{{baseUrl}}/procedures",
              "host": [
                "{{baseUrl}}"
              ],
              "path": [
                "procedures"
              ]
            }
          },
          "response": []
        },
        {
          "name": "Delete Procedure",
          "request": {
            "auth": {
              "type": "bearer",
              "bearer": [
                {
                  "key": "token",
                  "value": "{{token}}",
                  "type": "string"
                }
              ]
            },
            "method": "DELETE",
            "header": [],
            "url": {
              "raw": "{{baseUrl}}/procedures/{{procedureId}}",
              "host": [
                "{{baseUrl}}"
              ],
              "path": [
                "procedures",
                "{{procedureId}}"
              ]
            }
          },
          "response": []
        }
      ]
    },
    {
      "name": "Appointments",
      "item": [
        {
          "name": "Create Appointment",
          "event": [
            {
              "listen": "test",
              "script": {
                "exec": [
                  "pm.test(\"Create OK\", function () {",
                  "  pm.response.to.have.status(200);",
                  "});",
                  "",
                  "const json = pm.response.json();",
                  "pm.environment.set(\"appointmentId\", json.id);"
                ],
                "type": "text/javascript",
                "packages": {}
              }
            }
          ],
          "request": {
            "auth": {
              "type": "bearer",
              "bearer": [
                {
                  "key": "token",
                  "value": "{{token}}",
                  "type": "string"
                }
              ]
            },
            "method": "POST",
            "header": [],
            "body": {
              "mode": "raw",
              "raw": "{\n    \"patientId\": {{patientId}},\n    \"procedureId\": {{procedureId}},\n    \"userId\": {{userId}},\n    \"startTime\": \"2026-04-11T22:05:00.000Z\"\n}",
              "options": {
                "raw": {
                  "language": "json"
                }
              }
            },
            "url": {
              "raw": "{{baseUrl}}/appointments",
              "host": [
                "{{baseUrl}}"
              ],
              "path": [
                "appointments"
              ]
            }
          },
          "response": []
        },
        {
          "name": "Cancel Appointment",
          "event": [
            {
              "listen": "test",
              "script": {
                "exec": [
                  ""
                ],
                "type": "text/javascript",
                "packages": {}
              }
            }
          ],
          "request": {
            "auth": {
              "type": "bearer",
              "bearer": [
                {
                  "key": "token",
                  "value": "{{token}}",
                  "type": "string"
                }
              ]
            },
            "method": "POST",
            "header": [],
            "body": {
              "mode": "raw",
              "raw": "{\n    \"cancellationReason\": \"Motivo\"\n}",
              "options": {
                "raw": {
                  "language": "json"
                }
              }
            },
            "url": {
              "raw": "{{baseUrl}}/appointments/{{appointmentId}}/cancel",
              "host": [
                "{{baseUrl}}"
              ],
              "path": [
                "appointments",
                "{{appointmentId}}",
                "cancel"
              ]
            }
          },
          "response": []
        },
        {
          "name": "List Appointments",
          "request": {
            "auth": {
              "type": "bearer",
              "bearer": [
                {
                  "key": "token",
                  "value": "{{token}}",
                  "type": "string"
                }
              ]
            },
            "method": "GET",
            "header": [],
            "url": {
              "raw": "{{baseUrl}}/appointments",
              "host": [
                "{{baseUrl}}"
              ],
              "path": [
                "appointments"
              ]
            }
          },
          "response": []
        }
      ]
    }
  ],
  "auth": {
    "type": "awsv4"
  }
}